{
  "users": [
    {
      "id": "70d5",
      "email": "artyr_42@mail.ru",
      "password": "34r34r34r3"
    },
    {
      "email": "artyr_422@mail.ru",
      "password": "$2a$10$tXHG.XwQjjpmduRJXVsqkOY4T8/J9WxcGCCTK6HS5spcQ3PcqC6/2",
      "id": "xNqTKTY"
    },
    {
      "email": "artyr_4222@mail.ru",
      "password": "testpassword",
      "id": "h34cFBR"
    }
  ],
  "leaders": [
    {
      "changePersent": 64.8,
      "name": "Marketlove"
    },
    {
      "changePersent": 35.9,
      "name": "CrTrader"
    },
    {
      "changePersent": 28.3,
      "name": "Syngh"
    },
    {
      "changePersent": 28.2,
      "name": "Codecrypto"
    },
    {
      "changePersent": 23.3,
      "name": "Bitcoinbutler"
    },
    {
      "changePersent": 19.6,
      "name": "Coinunlike"
    },
    {
      "changePersent": 14.3,
      "name": "Coinfizzle"
    }
  ],
  "wallets": [
    {
      "userId": "xNqTKTY",
      "id": 3
    },
    {
      "id": 4,
      "userId": "h34cFBR",
      "totalValue": 154,
      "currencies": [
        {
          "name": "Gemini dollar",
          "value": 110,
          "iconUrl": "https://cdn.coinranking.com/s5cHqxxYr/gusd.svg",
          "symbol": "GUSD"
        },
        {
          "name": "Anchored Coins EUR",
          "value": 22,
          "iconUrl": "https://cdn.coinranking.com/6lCUSEget/ae.png",
          "symbol": "AEUR"
        },
        {
          "name": "Liquity USD",
          "value": 22,
          "iconUrl": "https://cdn.coinranking.com/nFn6b97om/9566.png",
          "symbol": "LUSD"
        }
      ]
    }
  ]
}